riqc/__init__.py
riqc/countGenes.py
riqc/riqc.py
riqc/scalingFactors.py
riqc/libs/__init__.py
riqc/libs/annotation.py
riqc/libs/bam.py
riqc/libs/bam_sparse.py
riqc/libs/kmer.py
riqc/libs/utils.py
riqc/libs/viz.py
riqc-0.2.0.dist-info/AUTHORS.md
riqc-0.2.0.dist-info/LICENSE
riqc-0.2.0.dist-info/METADATA
riqc-0.2.0.dist-info/WHEEL
riqc-0.2.0.dist-info/entry_points.txt
riqc-0.2.0.dist-info/top_level.txt
riqc-0.2.0.dist-info/RECORD
