Metadata-Version: 2.1
Name: riqc
Version: 0.2.0
Summary: Alignment-free RNA degradation tool
Home-page: https://github.com/ratschlab/riqc
Author: Kjong Lehmann, Andre Kahles
Author-email: kjong.lehmann@inf.ethz.ch, andre.kahles@inf.ethz.ch
License: MIT license
Keywords: riqc
Platform: UNKNOWN
Classifier: Development Status :: 2 - Pre-Alpha
Classifier: Intended Audience :: Developers
Classifier: License :: OSI Approved :: MIT License
Classifier: Natural Language :: English
Classifier: Programming Language :: Python :: 2
Classifier: Programming Language :: Python :: 2.7
Classifier: Programming Language :: Python :: 3
Classifier: Programming Language :: Python :: 3.4
Classifier: Programming Language :: Python :: 3.5
Classifier: Programming Language :: Python :: 3.6
Requires-Dist: h5py (==2.6.0)
Requires-Dist: matplotlib (==1.5.3)
Requires-Dist: pysam (==0.11.2.2)
Requires-Dist: pytest (==3.0.3)
Requires-Dist: scipy (==0.18.1)
